nrobo/__init__.py
nrobo/pypi_uploader.py
nrobo/version.py
nrobo/api_wrappers/__init__.py
nrobo/api_wrappers/api_wrapper.py
nrobo/cli/__init__.py
nrobo/cli/main.py
nrobo/cli/commands/__init__.py
nrobo/cli/commands/clean.py
nrobo/cli/commands/generate.py
nrobo/cli/commands/init.py
nrobo/cli/commands/nginx.py
nrobo/cli/commands/update.py
nrobo/core/__init__.py
nrobo/core/constants.py
nrobo/core/exceptions.py
nrobo/core/settings.py
nrobo/drivers/__init__.py
nrobo/drivers/base_driver.py
nrobo/drivers/driver_factory.py
nrobo/generators/__init__.py
nrobo/generators/page_generator.py
nrobo/helpers/__init__.py
nrobo/helpers/_pytest_helper.py
nrobo/helpers/_pytest_xdist.py
nrobo/helpers/api_factory.py
nrobo/helpers/arg_parsing.py
nrobo/helpers/cli_parser.py
nrobo/helpers/io_helper.py
nrobo/helpers/logging_extensions.py
nrobo/helpers/logging_helper.py
nrobo/helpers/network_utils.py
nrobo/helpers/nrobo_helper.py
nrobo/helpers/playwright_helper.py
nrobo/helpers/reporting_helper.py
nrobo/helpers/selenium_helper.py
nrobo/helpers/test_data_helper.py
nrobo/helpers/test_helper.py
nrobo/helpers/typing_logging.py
nrobo/helpers/validations.py
nrobo/locators/__init__.py
nrobo/locators/has_selector_parser.py
nrobo/locators/has_text_selector_parser.py
nrobo/locators/locator.py
nrobo/locators/locator_classifier.py
nrobo/locators/locator_collection.py
nrobo/locators/pseudo_selector_parser.py
nrobo/locators/shadow_selector_parser.py
nrobo/locators/text_selector_engine.py
nrobo/mixins/__init__.py
nrobo/mixins/auto_wait_mixin.py
nrobo/mixins/screenshot_mixin.py
nrobo/mixins/timeout_mixin.py
nrobo/mixins/window_mixin.py
nrobo/pages/__init__.py
nrobo/pages/base_page.py
nrobo/plugins/__init__.py
nrobo/plugins/detect_fixtures_plugin.py
nrobo/plugins/nrobo_plugin.py
nrobo/protocols/__init__.py
nrobo/protocols/web_driver_protocol.py
nrobo/protocols/web_element_protocol.py
nrobo/selenium_wrappers/__init__.py
nrobo/selenium_wrappers/action_chains.py
nrobo/selenium_wrappers/alerts.py
nrobo-2025.5.7.dist-info/licenses/LICENSE
nrobo-2025.5.7.dist-info/METADATA
nrobo-2025.5.7.dist-info/WHEEL
nrobo-2025.5.7.dist-info/entry_points.txt
nrobo-2025.5.7.dist-info/top_level.txt
nrobo-2025.5.7.dist-info/RECORD
