Metadata-Version: 2.4
Name: nrobo
Version: 2025.5.7
Summary: A Pytest-powered Smart Test Runner CLI tool.
Author-email: Panchdev Singh Chauhan <erpanchdev@gmail.com>
License: MIT
Requires-Python: >=3.10
License-File: LICENSE
Requires-Dist: pytest>=7.0
Requires-Dist: pytest-playwright
Requires-Dist: pyyaml
Requires-Dist: typer>=0.9
Requires-Dist: rich
Requires-Dist: pytest-html>=4.0.0
Requires-Dist: allure-pytest>=2.13.5
Requires-Dist: colorlog>=6.8.2
Requires-Dist: selenium>=4.12.0
Requires-Dist: Appium-Python-Client>=2.11.1
Requires-Dist: webdriver-manager>=4.0.1
Requires-Dist: coverage
Requires-Dist: tomlkit>=0.13.3
Requires-Dist: termcolor>=3.2.0
Requires-Dist: pytest-cov
Requires-Dist: pytest-xdist>=3.8.0
Requires-Dist: pytest-mock>=3.15.1
Requires-Dist: flake8
Requires-Dist: platformdirs
Requires-Dist: psutil
Requires-Dist: pre-commit
Requires-Dist: schemathesis
Requires-Dist: pyyaml
Requires-Dist: jsonschema
Requires-Dist: openapi-schema-validator
Requires-Dist: requests
Requires-Dist: requests-mock
Provides-Extra: dev
Requires-Dist: build; extra == "dev"
Requires-Dist: twine; extra == "dev"
Dynamic: license-file
